kante/__init__.py
kante/admin.py
kante/apps.py
kante/channel.py
kante/context.py
kante/path.py
kante/py.typed
kante/router.py
kante/schema.py
kante/type.py
kante/types.py
kante/consumers/__init__.py
kante/consumers/http.py
kante/consumers/ws.py
kante/middleware/cors.py
kante/migrations/__init__.py
kante/testing/__init__.py
kante/testing/http.py
kante/testing/ws.py
kante-0.16.1.dist-info/METADATA
kante-0.16.1.dist-info/WHEEL
kante-0.16.1.dist-info/RECORD
