Metadata-Version: 2.4
Name: kante
Version: 0.16.1
Author-email: jhnnsrs <jhnnsrs@gmail.com>
License-Expression: MIT
Requires-Python: <4.0,>=3.11
Requires-Dist: channels>=4.2.2
Requires-Dist: django>5
Requires-Dist: strawberry-graphql-django>=0.59.0
Requires-Dist: strawberry-graphql[channels]>=0.266.0
